netaddr-stubs/METADATA.toml
netaddr-stubs/__init__.pyi
netaddr-stubs/cli.pyi
netaddr-stubs/compat.pyi
netaddr-stubs/core.pyi
netaddr-stubs/fbsocket.pyi
netaddr-stubs/py.typed
netaddr-stubs/contrib/__init__.pyi
netaddr-stubs/contrib/subnet_splitter.pyi
netaddr-stubs/eui/__init__.pyi
netaddr-stubs/eui/ieee.pyi
netaddr-stubs/ip/__init__.pyi
netaddr-stubs/ip/glob.pyi
netaddr-stubs/ip/iana.pyi
netaddr-stubs/ip/nmap.pyi
netaddr-stubs/ip/rfc1924.pyi
netaddr-stubs/ip/sets.pyi
netaddr-stubs/strategy/__init__.pyi
netaddr-stubs/strategy/eui48.pyi
netaddr-stubs/strategy/eui64.pyi
netaddr-stubs/strategy/ipv4.pyi
netaddr-stubs/strategy/ipv6.pyi
types_netaddr-1.3.0.20260130.dist-info/licenses/LICENSE
types_netaddr-1.3.0.20260130.dist-info/METADATA
types_netaddr-1.3.0.20260130.dist-info/WHEEL
types_netaddr-1.3.0.20260130.dist-info/top_level.txt
types_netaddr-1.3.0.20260130.dist-info/RECORD
